orbs_orderbook/__init__.py
orbs_orderbook/client.py
orbs_orderbook/exceptions.py
orbs_orderbook/order_signer.py
orbs_orderbook/signer.py
orbs_orderbook/types.py
orbs_orderbook/utils.py
orbs_orderbook_sdk-0.10.2.dist-info/METADATA
orbs_orderbook_sdk-0.10.2.dist-info/WHEEL
orbs_orderbook_sdk-0.10.2.dist-info/RECORD
