Metadata-Version: 2.1
Name: orbs-orderbook-sdk
Version: 0.10.2
Summary: Python SDK for the Orbs order book
Author: Luke Rogerson
Author-email: contact@lukerogerson.me
Requires-Python: >=3.8,<4.0
Classifier: Programming Language :: Python :: 3
Classifier: Programming Language :: Python :: 3.8
Classifier: Programming Language :: Python :: 3.9
Classifier: Programming Language :: Python :: 3.10
Classifier: Programming Language :: Python :: 3.11
Classifier: Programming Language :: Python :: 3.12
Requires-Dist: asyncio (>=3.4.3,<4.0.0)
Requires-Dist: eth-account (>=0.10.0,<0.11.0)
Requires-Dist: requests (>=2.31.0,<3.0.0)
Requires-Dist: web3 (>=6.11.4,<7.0.0)
